material/rtl/full_adder.sv
`timescale 1ns / 1ps

module full_adder (
  input  logic a, b, ci,
  output logic sum, co
);
  logic wire_1, wire_2, wire_3;

  always_comb begin
    wire_1 = a ^ b;            // bitwise XOR
    wire_2 = wire_1 & ci;      // bitwise AND
    wire_3 = a & b;            // bitwise AND

    co     = wire_2 | wire_3;  // bitwise OR
    sum    = wire_1 ^ ci  ;    // bitwise XOR
  end

endmodule

material/rtl/n_adder.sv
`timescale 1ns / 1ps

module n_adder #(
  parameter N=4
)(
  input  logic signed [N-1:0] A, B,
  input  logic ci,
  output logic signed [N-1:0] S,
  output logic co
);
  logic C [N:0];
  assign C[0] = ci;
  assign co = C[N];

  genvar i; 
  for (i=0; i<N; i=i+1) begin:add
    // full_adder fa (A[i],B[i],C[i],C[i+1],S[i]);
    full_adder fa (
      .a    (A[i  ]),
      .b    (B[i  ]),
      .ci   (C[i  ]),
      .co   (C[i+1]),
      .sum  (S[i  ])
    );
  end
endmodule

material/tb/tb_n_adder.sv
`timescale 1ns / 1ps

module tb_n_adder;  
  localparam N = 8;

  logic signed [N-1:0] A, B, S;
  logic ci, co;
  
  bit [N-1:0] m;
  int status;

  n_adder #(.N(N)) dut (.*);

  initial begin
    $dumpfile("dump.vcd"); $dumpvars(0, dut);
    
    A = 8'd5; B = 8'd10; ci = 0;
    #1 assert (S == 8'd15) else $error("Fail");

    #10 A = 8'd30;  B = -8'd10; ci = 0;
    #10 A = 8'd5;   B = 8'd10;  ci = 1;
    #10 A = 8'd127; B = 8'd1;   ci = 0;

    repeat(10) begin
      #9
      status = std::randomize(ci);
      status = std::randomize(A) with { A inside {[-128:127]}; };
      status = std::randomize(B) with { B inside {[-128:127]}; };
      #1
      assert ({co,S} == A+B+ci)
        else $error("%d+%d+%d != {%d,%d}", A,B,ci,co,S);
    end
  end
endmodule

material/dump.vcd
$version Generated by VerilatedVcd $end
$timescale 1ps $end
 $scope module tb_n_adder $end
  $var wire 32 h N [31:0] $end
  $var wire 8 " A [7:0] $end
  $var wire 8 # B [7:0] $end
  $var wire 8 d S [7:0] $end
  $var wire 1 $ ci $end
  $var wire 1 e co $end
  $var wire 8 i m [7:0] $end
  $var wire 32 % status [31:0] $end
  $scope module dut $end
   $var wire 32 h N [31:0] $end
   $var wire 8 " A [7:0] $end
   $var wire 8 # B [7:0] $end
   $var wire 1 $ ci $end
   $var wire 8 d S [7:0] $end
   $var wire 1 e co $end
   $var wire 1 > C[0] $end
   $var wire 1 ? C[1] $end
   $var wire 1 @ C[2] $end
   $var wire 1 A C[3] $end
   $var wire 1 B C[4] $end
   $var wire 1 C C[5] $end
   $var wire 1 D C[6] $end
   $var wire 1 E C[7] $end
   $var wire 1 F C[8] $end
   $scope module add[0] $end
    $scope module fa $end
     $var wire 1 & a $end
     $var wire 1 ' b $end
     $var wire 1 $ ci $end
     $var wire 1 f sum $end
     $var wire 1 G co $end
     $var wire 1 H wire_1 $end
     $var wire 1 g wire_2 $end
     $var wire 1 ( wire_3 $end
    $upscope $end
   $upscope $end
   $scope module add[1] $end
    $scope module fa $end
     $var wire 1 ) a $end
     $var wire 1 * b $end
     $var wire 1 G ci $end
     $var wire 1 I sum $end
     $var wire 1 J co $end
     $var wire 1 K wire_1 $end
     $var wire 1 L wire_2 $end
     $var wire 1 + wire_3 $end
    $upscope $end
   $upscope $end
   $scope module add[2] $end
    $scope module fa $end
     $var wire 1 , a $end
     $var wire 1 - b $end
     $var wire 1 J ci $end
     $var wire 1 M sum $end
     $var wire 1 N co $end
     $var wire 1 O wire_1 $end
     $var wire 1 P wire_2 $end
     $var wire 1 . wire_3 $end
    $upscope $end
   $upscope $end
   $scope module add[3] $end
    $scope module fa $end
     $var wire 1 / a $end
     $var wire 1 0 b $end
     $var wire 1 N ci $end
     $var wire 1 Q sum $end
     $var wire 1 R co $end
     $var wire 1 S wire_1 $end
     $var wire 1 T wire_2 $end
     $var wire 1 1 wire_3 $end
    $upscope $end
   $upscope $end
   $scope module add[4] $end
    $scope module fa $end
     $var wire 1 2 a $end
     $var wire 1 3 b $end
     $var wire 1 R ci $end
     $var wire 1 U sum $end
     $var wire 1 V co $end
     $var wire 1 W wire_1 $end
     $var wire 1 X wire_2 $end
     $var wire 1 4 wire_3 $end
    $upscope $end
   $upscope $end
   $scope module add[5] $end
    $scope module fa $end
     $var wire 1 5 a $end
     $var wire 1 6 b $end
     $var wire 1 V ci $end
     $var wire 1 Y sum $end
     $var wire 1 Z co $end
     $var wire 1 [ wire_1 $end
     $var wire 1 \ wire_2 $end
     $var wire 1 7 wire_3 $end
    $upscope $end
   $upscope $end
   $scope module add[6] $end
    $scope module fa $end
     $var wire 1 8 a $end
     $var wire 1 9 b $end
     $var wire 1 Z ci $end
     $var wire 1 ] sum $end
     $var wire 1 ^ co $end
     $var wire 1 _ wire_1 $end
     $var wire 1 ` wire_2 $end
     $var wire 1 : wire_3 $end
    $upscope $end
   $upscope $end
   $scope module add[7] $end
    $scope module fa $end
     $var wire 1 ; a $end
     $var wire 1 < b $end
     $var wire 1 ^ ci $end
     $var wire 1 a sum $end
     $var wire 1 e co $end
     $var wire 1 b wire_1 $end
     $var wire 1 c wire_2 $end
     $var wire 1 = wire_3 $end
    $upscope $end
   $upscope $end
  $upscope $end
 $upscope $end
$enddefinitions $end


#0
b00000101 "
b00001010 #
0$
b00000000000000000000000000000000 %
1&
0'
0(
0)
1*
0+
1,
0-
0.
0/
10
01
02
03
04
05
06
07
08
09
0:
0;
0<
0=
0>
0?
0@
0A
0B
0C
0D
0E
0F
0G
1H
1I
0J
1K
0L
1M
0N
1O
0P
1Q
0R
1S
0T
0U
0V
0W
0X
0Y
0Z
0[
0\
0]
0^
0_
0`
0a
0b
0c
b00001111 d
0e
1f
0g
b00000000000000000000000000001000 h
b00000000 i
#11000
b00011110 "
b11110110 #
0&
1)
1+
1-
1.
1/
00
12
13
14
16
19
1<
1@
1A
1B
1C
1D
1E
1F
0H
0I
1J
0K
1N
0O
0Q
1R
1T
1U
1V
1Z
1[
1\
1^
1_
1`
1b
1c
b00010100 d
1e
0f
#21000
b00000101 "
b00001010 #
1$
1&
0)
0+
0-
0.
0/
10
02
03
04
06
09
0<
1>
1?
0C
0D
0E
0F
1G
1H
1K
1L
0M
1O
1P
0V
0Z
0[
0\
0^
0_
0`
0b
0c
b00010000 d
0e
1g
#31000
b01111111 "
b00000001 #
0$
1'
1(
1)
0*
1/
00
12
15
18
0>
1C
1D
1E
0H
0U
1V
1W
1X
1Z
1[
1\
1^
1_
1`
1a
b10000000 d
0g
#40000
b01001011 "
b00101011 #
1$
b00000000000000000000000000000001 %
1*
1+
0,
10
11
02
05
16
1>
0A
0C
0D
0E
1I
0K
0L
1M
0N
0O
0P
0S
0T
1U
0V
0W
0X
1Y
0Z
0\
1]
0^
0`
0a
b01110111 d
1f
#50000
b10001111 "
b01011101 #
0*
0+
1,
1-
1.
13
06
08
19
1;
1A
1C
0I
1K
1L
1N
1Q
0U
1V
1W
1X
0[
1a
1b
b11101101 d
#60000
b00000111 "
b01011001 #
0-
0.
0/
01
0;
0M
1O
1P
0Q
1S
1T
0a
0b
b01100001 d
#70000
b10011011 "
b10111110 #
0'
0(
1*
1+
0,
1-
1/
11
12
14
16
09
1;
1<
1=
1D
1F
1H
1I
0K
0L
1Q
0S
0T
1U
0W
0X
0Y
1Z
1[
1\
0_
b01011010 d
1e
0f
1g
#80000
b10010011 "
b01010101 #
0$
1'
1(
0*
0+
0/
00
01
06
19
0<
0=
0>
0B
0D
0F
0H
0I
1K
1L
0R
0U
1Y
0Z
0[
0\
1_
1a
1b
b11101000 d
0e
0g
#90000
b11100011 "
b10000111 #
1$
1*
1+
02
03
04
15
18
09
1<
1=
1>
0C
1F
1I
0K
0L
0V
1[
0a
0b
b01101011 d
1e
1f
#100000
b00011010 "
b10010011 #
0&
0(
0-
1/
12
13
14
05
08
0;
0=
0A
1C
0F
1H
1M
0N
0O
0P
1S
1V
0[
0]
0_
1a
1b
b10101110 d
0e
0f
1g
#110000
b00001001 "
b10110001 #
0$
1&
1(
0)
0*
0+
02
04
16
0>
0@
0C
0H
0J
0M
1U
0V
1W
1[
b10111010 d
0g
#120000
b11010101 "
b11100101 #
1,
1-
1.
0/
12
03
18
19
1:
1;
1=
1A
1E
1F
1N
0S
1^
0b
1e
#130000
b00101111 "
b11110101 #
1$
1)
1/
02
13
15
17
08
0:
0;
0=
1>
1@
1B
1C
1D
0I
1J
1K
1L
1M
0Q
1R
1S
1T
0U
1V
1X
1Z
0[
1_
1`
0a
1b
1c
b00100101 d
1f
